{
  "name": "Watchman Pack",
  "type": "starterPack",
  "img": "icons/sundries/lights/lantern-bullseye-signal-copper.webp",
  "system": {
    "description": "",
    "items": [
      {
        "uuid": "Compendium.vagabond.gear.Item.8o8KVSgpYsNFtGz2",
        "quantity": 1
      },
      {
        "uuid": "Compendium.vagabond.gear.Item.YHXzL4H8Dhajk2hg",
        "quantity": 1
      },
      {
        "uuid": "Compendium.vagabond.gear.Item.BhUNyj2nflyVUPIo",
        "quantity": 5
      },
      {
        "uuid": "Compendium.vagabond.gear.Item.sbHg7jCRQY8lIzY7",
        "quantity": 2
      },
      {
        "uuid": "Compendium.vagabond.gear.Item.jd6n1Zfo1tAWCCNe",
        "quantity": 1
      },
      {
        "uuid": "Compendium.vagabond.weapons.Item.vOF4iFi5ieztUI7N",
        "quantity": 1
      },
      {
        "uuid": "Compendium.vagabond.weapons.Item.ZPaSkHYlIBVwUQdO",
        "quantity": 1
      },
      {
        "uuid": "Compendium.vagabond.gear.Item.pVe3gBnfzcmqyMgM",
        "quantity": 1
      },
      {
        "uuid": "Compendium.vagabond.armor.Item.T5aaqoo4V8KZIVCZ",
        "quantity": 1
      },
      {
        "uuid": "Compendium.vagabond.gear.Item.WkEFG0QhS4QJ6NwL",
        "quantity": 1
      },
      {
        "uuid": "Compendium.vagabond.gear.Item.2wYFUy46hK86VuAJ",
        "quantity": 1
      }
    ],
    "currency": {
      "gold": 0,
      "silver": 33,
      "copper": 0
    }
  },
  "effects": [],
  "folder": null,
  "flags": {},
  "_stats": {
    "compendiumSource": null,
    "duplicateSource": null,
    "exportSource": null,
    "coreVersion": "13.351",
    "systemId": "vagabond",
    "systemVersion": "1.3.4",
    "createdTime": 1765640510531,
    "modifiedTime": 1765640522942,
    "lastModifiedBy": "13p65OEadZSZVLRk"
  },
  "ownership": {
    "default": 0,
    "13p65OEadZSZVLRk": 3
  },
  "_id": "X4shfsU5ixmg1J4O",
  "sort": 3500000,
  "_key": "!items!X4shfsU5ixmg1J4O"
}
