{
  "name": "Sylph Scope",
  "type": "equipment",
  "img": "icons/magic/symbols/circled-gem-pink.webp",
  "system": {
    "description": "<p><span class=\"fontstyle0\">A set of glasses that grant the following Powers to those who wear them:</span></p><ul><li><span class=\"fontstyle2\">Allsight:</span><span class=\"fontstyle0\"> Can see Invisible Beings.</span></li></ul>",
    "equipmentType": "relic",
    "locked": true,
    "equipped": false,
    "quantity": 1,
    "baseCost": {
      "gold": 1000,
      "silver": 0,
      "copper": 0
    },
    "baseSlots": 1,
    "metal": "none",
    "damageType": "-",
    "damageAmount": "",
    "properties": [],
    "weaponSkill": "melee",
    "range": "close",
    "grip": "1H",
    "damageOneHand": "d6",
    "damageTwoHands": "d8",
    "equipmentState": "unequipped",
    "armorType": "light",
    "immunities": [],
    "gearCategory": "",
    "alchemicalType": "",
    "lore": "Relic Glasses"
  },
  "effects": [],
  "folder": null,
  "flags": {},
  "_stats": {
    "compendiumSource": null,
    "duplicateSource": null,
    "exportSource": null,
    "coreVersion": "13.351",
    "systemId": "vagabond",
    "systemVersion": "3.0.0",
    "createdTime": 1764967025119,
    "modifiedTime": 1766160276298,
    "lastModifiedBy": "13p65OEadZSZVLRk"
  },
  "_id": "oj96KcGFe7iT6ayG",
  "ownership": {
    "default": 0,
    "vJkLjvlErdx6ZHoC": 3
  },
  "sort": 3500000,
  "_key": "!items!oj96KcGFe7iT6ayG"
}
