{
  "name": "Ale/Cider - Barrel, small",
  "type": "equipment",
  "img": "icons/containers/barrels/barrel-oak-tan.webp",
  "system": {
    "description": "",
    "equipmentType": "gear",
    "locked": true,
    "equipped": false,
    "quantity": 1,
    "baseCost": {
      "gold": 0,
      "silver": 20,
      "copper": 0
    },
    "baseSlots": 1,
    "metal": "none",
    "damageType": "-",
    "damageAmount": "",
    "canExplode": false,
    "explodeValues": "",
    "properties": [],
    "weaponSkill": "melee",
    "range": "close",
    "grip": "1H",
    "damageOneHand": "d6",
    "damageTwoHands": "d8",
    "equipmentState": "unequipped",
    "armorType": "light",
    "immunities": [],
    "gearCategory": "Liquor & Spirits",
    "alchemicalType": "concoction",
    "lore": "",
    "isBeverage": true
  },
  "effects": [],
  "flags": {
    "core": {}
  },
  "_stats": {
    "compendiumSource": "Item.Ofpjo0aJto6jKJI3",
    "duplicateSource": null,
    "exportSource": null,
    "coreVersion": "13.351",
    "systemId": "vagabond",
    "systemVersion": "3.7.0",
    "createdTime": 1765502288108,
    "modifiedTime": 1771788217716,
    "lastModifiedBy": "13p65OEadZSZVLRk"
  },
  "_id": "8rcvjaFmsSHTqNJI",
  "folder": "KlLsMy7yqvvnIJRq",
  "sort": 0,
  "ownership": {
    "default": 0,
    "13p65OEadZSZVLRk": 3
  },
  "_key": "!items!8rcvjaFmsSHTqNJI"
}
